{"trial_id": "03", "hyperparameters": {"space": [{"class_name": "Int", "config": {"name": "units_1", "default": null, "conditions": [], "min_value": 32, "max_value": 128, "step": 32, "sampling": "linear"}}, {"class_name": "Int", "config": {"name": "units_2", "default": null, "conditions": [], "min_value": 16, "max_value": 64, "step": 16, "sampling": "linear"}}, {"class_name": "Float", "config": {"name": "dropout", "default": 0.2, "conditions": [], "min_value": 0.2, "max_value": 0.5, "step": 0.1, "sampling": "linear"}}, {"class_name": "Int", "config": {"name": "dense_units", "default": null, "conditions": [], "min_value": 16, "max_value": 64, "step": 16, "sampling": "linear"}}, {"class_name": "Choice", "config": {"name": "learning_rate", "default": 0.001, "conditions": [], "values": [0.001, 0.0001], "ordered": true}}], "values": {"units_1": 64, "units_2": 16, "dropout": 0.2, "dense_units": 32, "learning_rate": 0.0001}}, "metrics": {"metrics": {"accuracy": {"direction": "max", "observations": [{"value": [0.9751054048538208], "step": 49}]}, "loss": {"direction": "min", "observations": [{"value": [0.08222448825836182], "step": 49}]}, "val_accuracy": {"direction": "max", "observations": [{"value": [0.9825897812843323], "step": 49}]}, "val_loss": {"direction": "min", "observations": [{"value": [0.05520451441407204], "step": 49}]}}}, "score": 0.05520451441407204, "best_step": 49, "status": "COMPLETED", "message": null}